pixelmatch/__init__.py
pixelmatch/cli.py
pixelmatch/py.typed
pixelmatch_fast-1.3.2.dist-info/METADATA
pixelmatch_fast-1.3.2.dist-info/WHEEL
pixelmatch_fast-1.3.2.dist-info/entry_points.txt
pixelmatch_fast-1.3.2.dist-info/licenses/LICENSE
pixelmatch_fast-1.3.2.dist-info/RECORD
