Metadata-Version: 2.4
Name: pixelmatch-fast
Version: 1.3.2
Summary: High-performance Python port of mapbox/pixelmatch for perceptual image comparison
Project-URL: Homepage, https://github.com/JustusRijke/pixelmatch-fast
Project-URL: Issues, https://github.com/JustusRijke/pixelmatch-fast/issues
Author-email: Justus Rijke <justusrijke@gmail.com>
License-Expression: MIT
License-File: LICENSE
Classifier: Development Status :: 5 - Production/Stable
Classifier: Operating System :: Microsoft :: Windows
Classifier: Operating System :: POSIX :: Linux
Classifier: Programming Language :: Python :: 3
Classifier: Typing :: Typed
Requires-Python: >=3.10.0
Requires-Dist: click>=8
Requires-Dist: numba>=0.57
Requires-Dist: numpy>=1.22.3
Requires-Dist: pillow>=10
Requires-Dist: pre-commit>=4.5.1
